django_github_revision-0.0.3.dist-info/DESCRIPTION.rst
django_github_revision-0.0.3.dist-info/METADATA
django_github_revision-0.0.3.dist-info/RECORD
django_github_revision-0.0.3.dist-info/WHEEL
django_github_revision-0.0.3.dist-info/metadata.json
django_github_revision-0.0.3.dist-info/top_level.txt
github_revision/__init__.py
github_revision/apps.py
github_revision/backends.py
github_revision/context_processors.py
github_revision/models.py
github_revision/settings.py
github_revision/tests.py
github_revision/utils.py
github_revision/templatetags/__init__.py
github_revision/templatetags/github_revision_tags.py
