Metadata-Version: 2.0
Name: django-github-revision
Version: 0.0.3
Summary: Publishes information about the git revision that is running and links to the GitHub repository.
Home-page: https://github.com/watchdogpolska/django-github-revision
Author: Adam Dobrawy
Author-email: karol.bregula@siecobywatelska.pl
License: MIT
Platform: UNKNOWN
Requires-Dist: dealer
Requires-Dist: django
Provides-Extra: tests
Requires-Dist: mock; extra == 'tests'
